aunly_bbot/__main__.py
aunly_bbot/bot.py
aunly_bbot/cli/__init__.py
aunly_bbot/cli/api.py
aunly_bbot/cli/config.py
aunly_bbot/cli/run.py
aunly_bbot/core/__init__.py
aunly_bbot/core/announcement.py
aunly_bbot/core/bot_config.py
aunly_bbot/core/context.py
aunly_bbot/core/control.py
aunly_bbot/core/data.py
aunly_bbot/core/group_config.py
aunly_bbot/core/log.py
aunly_bbot/core/subgroup_config.py
aunly_bbot/function/__init__.py
aunly_bbot/function/command/add_talk.py
aunly_bbot/function/command/admin/add.py
aunly_bbot/function/command/admin/remove.py
aunly_bbot/function/command/announcement.py
aunly_bbot/function/command/configure/atall.py
aunly_bbot/function/command/configure/nick.py
aunly_bbot/function/command/content_resolve.py
aunly_bbot/function/command/init.py
aunly_bbot/function/command/menu/__init__.py
aunly_bbot/function/command/quit_group.py
aunly_bbot/function/command/status.py
aunly_bbot/function/command/subgroup/add.py
aunly_bbot/function/command/subgroup/add_up.py
aunly_bbot/function/command/subgroup/get_subgroup.py
aunly_bbot/function/command/subgroup/remove.py
aunly_bbot/function/command/subgroup/remove_up.py
aunly_bbot/function/command/up/get_subscribe.py
aunly_bbot/function/command/up/subscribe.py
aunly_bbot/function/command/up/unsubscribe.py
aunly_bbot/function/command/vip/add.py
aunly_bbot/function/command/vip/remove.py
aunly_bbot/function/command/vive_dynamic.py
aunly_bbot/function/command/web_auth.py
aunly_bbot/function/command/whitelist/add.py
aunly_bbot/function/command/whitelist/close.py
aunly_bbot/function/command/whitelist/open.py
aunly_bbot/function/command/whitelist/remove.py
aunly_bbot/function/event/bot_launch.py
aunly_bbot/function/event/exception.py
aunly_bbot/function/event/invited_join_group.py
aunly_bbot/function/event/join_group.py
aunly_bbot/function/event/leave_group.py
aunly_bbot/function/event/mute.py
aunly_bbot/function/event/new_friend.py
aunly_bbot/function/event/offline.py
aunly_bbot/function/event/prem_change.py
aunly_bbot-1.6.1.dist-info/entry_points.txt
aunly_bbot-1.6.1.dist-info/WHEEL
aunly_bbot-1.6.1.dist-info/METADATA
aunly_bbot-1.6.1.dist-info/licenses/LICENSE
aunly_bbot-1.6.1.dist-info/RECORD
