Metadata-Version: 2.1
Name: aunly-bbot
Version: 1.6.1
Summary: 一个用于 QQ 群内高效推送哔哩哔哩 UP 动态及直播的机器人
License: AGPL3.0
Keywords: graia,graiax,bilibili,qqbot,grpc,playwright,fastapi,bot,openai,chatgpt
Author-email: djkcyl <cyl@cyllive.cn>
Requires-Python: >=3.9,<4.0
Requires-Dist: bilireq>=0.2.11
Requires-Dist: fastapi>=0.97.0
Requires-Dist: graia-ariadne[standard]>=0.11.5
Requires-Dist: lxml>=4.9.2
Requires-Dist: minidynamicrender>=1.2.6
Requires-Dist: noneprompt>=0.1.9
Requires-Dist: passlib[bcrypt]>=1.7.4
Requires-Dist: peewee>=3.16.2
Requires-Dist: pillow>=9.5.0
Requires-Dist: psutil>=5.9.5
Requires-Dist: python-jose[cryptography]>=3.3.0
Requires-Dist: python-multipart>=0.0.6
Requires-Dist: pyyaml>=6.0
Requires-Dist: qrcode>=7.4.2
Requires-Dist: sentry-sdk>=1.25.1
Requires-Dist: tiktoken-async>=0.3.2
Requires-Dist: uvicorn>=0.22.0
Requires-Dist: websockets>=11.0.3
Provides-Extra: full
Requires-Dist: graiax-playwright>=0.2.4; extra == "full"
Requires-Dist: graiax-text2img-playwright>=0.4.0; extra == "full"
Requires-Dist: wordcloud>=1.9.2; extra == "full"
Requires-Dist: jieba>=0.42.1; extra == "full"
Requires-Dist: jinja2>=3.1.2; extra == "full"
Project-URL: documentation, https://github.com/djkcyl/BBot-Graia/blob/master/readme.md
Project-URL: homepage, https://github.com/djkcyl/BBot-Graia
Project-URL: repository, https://github.com/djkcyl/BBot-Graia/tree/master/bbot
